markovflow/__init__.py
markovflow/base.py
markovflow/block_tri_diag.py
markovflow/conditionals.py
markovflow/emission_model.py
markovflow/gauss_markov.py
markovflow/kalman_filter.py
markovflow/kernels/__init__.py
markovflow/kernels/constant.py
markovflow/kernels/kernel.py
markovflow/kernels/latent_exp_generated.py
markovflow/kernels/matern.py
markovflow/kernels/periodic.py
markovflow/kernels/piecewise_stationary.py
markovflow/kernels/sde_kernel.py
markovflow/likelihoods/__init__.py
markovflow/likelihoods/likelihoods.py
markovflow/likelihoods/multivariate_gaussian.py
markovflow/likelihoods/mutlistage_likelihood.py
markovflow/mean_function.py
markovflow/models/__init__.py
markovflow/models/gaussian_process_regression.py
markovflow/models/iwvi.py
markovflow/models/models.py
markovflow/models/pep.py
markovflow/models/sparse_pep.py
markovflow/models/sparse_variational.py
markovflow/models/sparse_variational_cvi.py
markovflow/models/spatio_temporal_variational.py
markovflow/models/variational.py
markovflow/models/variational_cvi.py
markovflow/posterior.py
markovflow/ssm_gaussian_transformations.py
markovflow/ssm_natgrad.py
markovflow/state_space_model.py
markovflow/utils.py
markovflow-0.0.1.dist-info/WHEEL
markovflow-0.0.1.dist-info/METADATA
markovflow-0.0.1.dist-info/RECORD
