Metadata-Version: 2.1
Name: markovflow
Version: 0.0.1
Summary: A Tensorflow based library for Time Series Modelling with Gaussian Processes
Author: Markovflow Contributors
Author-email: markovflow@secondmind.ai
Requires-Python: >3.7,<3.8
Classifier: Programming Language :: Python :: 3
Requires-Dist: banded-matrices (==0.0.6)
Requires-Dist: google-auth (>=1.16.0,<2.0.0)
Requires-Dist: gpflow (>=2.1,<3.0)
Requires-Dist: importlib_metadata (>=1.6,<2.0)
Requires-Dist: numpy (>=1.18.0,<2.0.0)
Requires-Dist: scipy (>=1.4.1,<2.0.0)
Requires-Dist: setuptools (>=41.0.0,<42.0.0)
Requires-Dist: tensorflow (>2.2.0)
Requires-Dist: tensorflow-probability (==0.11.0)
